funcfolio/__init__.py
funcfolio-0.0.0.dist-info/WHEEL
funcfolio-0.0.0.dist-info/METADATA
funcfolio-0.0.0.dist-info/RECORD
