Metadata-Version: 2.3
Name: funcfolio
Version: 0.0.0
Summary: funcfolio
Requires-Python: >=3.8
